agent_society_lib-0.1.16.dist-info/licenses/LICENSE
agentsociety/__init__.py
agentsociety/constants.py
agentsociety/embedding.py
agentsociety/log.py
agentsociety/prompting.py
agentsociety/utils.py
agentsociety/worker.py
agentsociety/chat/__init__.py
agentsociety/chat/artifact.py
agentsociety/chat/history.py
agentsociety/chat/utils.py
agentsociety/chat/box/__init__.py
agentsociety/chat/box/free_flow_box.py
agentsociety/chat/box/free_flow_graph.py
agentsociety/chat/box/shared.py
agentsociety/chat/free/__init__.py
agentsociety/chat/free/routers.py
agentsociety/chat/intent/__init__.py
agentsociety/chat/intent/intent_router.py
agent_society_lib-0.1.16.dist-info/METADATA
agent_society_lib-0.1.16.dist-info/WHEEL
agent_society_lib-0.1.16.dist-info/top_level.txt
agent_society_lib-0.1.16.dist-info/RECORD
