Metadata-Version: 2.4
Name: agent-society-lib
Version: 0.1.16
Summary: A Python Library that integrates with the agent-society server
Author: Agent Society
License: Copyright 2025 Agent Society
Classifier: Programming Language :: Python :: 3
Classifier: License :: OSI Approved :: MIT License
Classifier: Operating System :: OS Independent
Requires-Python: >=3.12.8
License-File: LICENSE
Requires-Dist: pytest
Requires-Dist: jinja2
Requires-Dist: redis
Requires-Dist: chromadb==0.5.0
Requires-Dist: pika
Requires-Dist: langchain
Requires-Dist: langchain-openai
Requires-Dist: langchain-groq
Requires-Dist: langchain-google-genai
Requires-Dist: openai>=1.58.1
Requires-Dist: numpy<2.0.0,>=1.26.4
Dynamic: license-file
